divi/__init__.py
divi/backends/__init__.py
divi/backends/_backend_properties_conversion.py
divi/backends/_circuit_runner.py
divi/backends/_execution_result.py
divi/backends/_parallel_simulator.py
divi/backends/_qoro_service.py
divi/backends/_qpu_system.py
divi/backends/_results_processing.py
divi/circuits/__init__.py
divi/circuits/_cirq/__init__.py
divi/circuits/_cirq/_parser.py
divi/circuits/_cirq/_qasm_export.py
divi/circuits/_core.py
divi/circuits/_qasm_conversion.py
divi/circuits/_qasm_validation.py
divi/circuits/qem.py
divi/qprog/__init__.py
divi/qprog/_expectation.py
divi/qprog/_hamiltonians.py
divi/qprog/algorithms/__init__.py
divi/qprog/algorithms/_ansatze.py
divi/qprog/algorithms/_custom_vqa.py
divi/qprog/algorithms/_pce.py
divi/qprog/algorithms/_qaoa.py
divi/qprog/algorithms/_vqe.py
divi/qprog/batch.py
divi/qprog/checkpointing.py
divi/qprog/exceptions.py
divi/qprog/optimizers.py
divi/qprog/quantum_program.py
divi/qprog/typing.py
divi/qprog/variational_quantum_algorithm.py
divi/qprog/workflows/__init__.py
divi/qprog/workflows/_graph_partitioning.py
divi/qprog/workflows/_qubo_partitioning.py
divi/qprog/workflows/_vqe_sweep.py
divi/reporting/__init__.py
divi/reporting/_pbar.py
divi/reporting/_qlogger.py
divi/reporting/_reporter.py
qoro_divi-0.6.1.dist-info/METADATA
qoro_divi-0.6.1.dist-info/WHEEL
qoro_divi-0.6.1.dist-info/licenses/LICENSE
qoro_divi-0.6.1.dist-info/licenses/LICENSES/.license-header
qoro_divi-0.6.1.dist-info/licenses/LICENSES/Apache-2.0.txt
qoro_divi-0.6.1.dist-info/RECORD
